{
  "id": "crossref_10.2307_2036168",
  "doi": "10.2307/2036168",
  "title": "The Eilenberg-Moore, Rothenberg-Steenrod Spectral Sequence for K Theory",
  "authors": [
    "Petrie, Ted"
  ],
  "author_string": "Petrie, Ted",
  "journal": "Proceedings of the American Mathematical Society",
  "issn": "0002-9939",
  "issn_type": "print",
  "volume": "19",
  "issue": "1",
  "page": "193",
  "year": "1968",
  "publisher": "JSTOR",
  "language": "",
  "abstract": "",
  "subjects": [],
  "keywords": [],
  "article_type": "journal-article",
  "citation_count": 1,
  "url": "https://doi.org/10.2307/2036168",
  "source": "crossref",
  "acquired_date": "2026-02-03T13:06:59.691339",
  "category": "mathematics",
  "subcategories": []
}