{
  "id": "arxiv_1008.3822v2",
  "arxiv_id": "1008.3822v2",
  "title": "A model for the Delta(1600) resonance and gamma N -> Delta(1600) transition",
  "authors": [
    "G. Ramalho",
    "K. Tsushima"
  ],
  "author_string": "G. Ramalho, K. Tsushima",
  "journal": "Phys.Rev.D82:073007,2010",
  "journal_ref": "Phys.Rev.D82:073007,2010",
  "year": "2010",
  "doi": "10.1103/PhysRevD.82.073007",
  "abstract": "A covariant spectator constituent quark model is applied to study the gamma N -> Delta(1600) transition. Two processes are important in the transition: a photon couples to the individual quarks of the Delta(1600) core (quark core), and a photon couples to the intermediate pion-baryon states (pion cloud). While the quark core contributions are estimated assuming Delta(1600) as the first radial excitation of Delta(1232), the pion cloud contributions are estimated based on an analogy with the gamma N -> Delta(1232) transition. To estimate the pion cloud contributions in the gamma N -> Delta(1600) transition, we include the relevant intermediate states, pi-N, pi-Delta, pi-N(1440) and pi-Delta(1600). Dependence on the four-momentum transfer squared, Q2, is predicted for the magnetic dipole transition form factor, GM*(Q2), as well as the helicity amplitudes, A_1/2(Q2) and A_3/2(Q2). The results at Q2=0 are compared with the existing data.",
  "categories": [
    "hep-ph",
    "hep-ex",
    "hep-lat",
    "nucl-ex",
    "nucl-th"
  ],
  "primary_category": "nucl-th",
  "comment": "To appear in Phys. Rev. D. Version with small modifications. 14 pages, 6 figures and 3 tables",
  "published_date": "2010-08-23T13:45:42Z",
  "updated_date": "2010-09-08T15:36:09Z",
  "url": "https://arxiv.org/abs/1008.3822v2",
  "pdf_url": "https://arxiv.org/pdf/1008.3822v2.pdf",
  "source": "arxiv",
  "acquired_date": "2026-02-03T13:20:42.313963",
  "category": "physics",
  "subcategories": [
    "hep-ph",
    "hep-ex",
    "hep-lat"
  ]
}