{
  "id": "arxiv_1208.4058v1",
  "arxiv_id": "1208.4058v1",
  "title": "DbarN interaction in a color-confining chiral quark model",
  "authors": [
    "C. E. Fontoura",
    "G. Krein",
    "V. E. Vizcarra"
  ],
  "author_string": "C. E. Fontoura, G. Krein, V. E. Vizcarra",
  "journal": "arXiv:1208.4058v1",
  "journal_ref": null,
  "year": "2012",
  "doi": "10.1103/PhysRevC.87.025206",
  "abstract": "We investigate the low-energy elastic DbarN interaction using a quark model that confines color and realizes dynamical chiral symmetry breaking. The model is defined by a microscopic Hamiltonian inspired in the QCD Hamiltonian in Coulomb gauge. Constituent quark masses are obtained by solving a gap equation and baryon and meson bound-state wave functions are obtained using a variational method. We derive a low energy meson-nucleon potential from a quark-interchange mechanism whose ingredients are the quark-quark and quark-antiquark interactions and baryon and meson wave functions, all derived from the same microscopic Hamiltonian. The model is supplemented with (sigma,rho,omega,a0) single-meson exchanges to describe the long-range part of the interaction. Cross-sections and phase shifts are obtained by iterating the quark-interchange plus meson-exchange potentials in a Lippmann-Schwinger equation. Once model parameters in meson exchange potential are fixed to describe the low-energy experimental phase shifts of the K+N and K0N reactions, predictions for Dbar0N and D-N reactions are obtained without introducing new parameters.",
  "categories": [
    "nucl-th",
    "hep-ex",
    "hep-lat",
    "hep-ph",
    "nucl-ex"
  ],
  "primary_category": "nucl-ex",
  "comment": "13 latex pages, 7 figures",
  "published_date": "2012-08-20T17:12:44Z",
  "updated_date": "2012-08-20T17:12:44Z",
  "url": "https://arxiv.org/abs/1208.4058v1",
  "pdf_url": "https://arxiv.org/pdf/1208.4058v1.pdf",
  "source": "arxiv",
  "acquired_date": "2026-02-03T13:20:34.600837",
  "category": "physics",
  "subcategories": [
    "nucl-th",
    "hep-ex",
    "hep-lat"
  ]
}