{
  "id": "arxiv_2601.11086v1",
  "arxiv_id": "2601.11086v1",
  "title": "Converting qubit relaxation into erasures with a single fluxonium",
  "authors": [
    "Chenlu Liu",
    "Yulong Li",
    "Jiahui Wang",
    "Quan Guan",
    "Lijing Jin",
    "Lu Ma",
    "Ruizi Hu",
    "Tenghui Wang",
    "Xing Zhu",
    "Hai-Feng Yu",
    "Chunqing Deng",
    "Xizheng Ma"
  ],
  "author_string": "Chenlu Liu, Yulong Li, Jiahui Wang, Quan Guan, Lijing Jin et al.",
  "journal": "arXiv:2601.11086v1",
  "journal_ref": null,
  "year": "2026",
  "doi": null,
  "abstract": "Qubits that experience predominantly erasure errors offer distinct advantages for fault-tolerant operation. Indeed, dual-rail encoded erasure qubits in superconducting cavities and transmons have demonstrated high-fidelity operations by converting physical-qubit relaxation into logical-qubit erasures, but this comes at the cost of increased hardware overhead and circuit complexity. Here, we address these limitations by realizing erasure conversion in a single fluxonium operated at zero flux, where the logical state is encoded in its 0-2 subspace. A single, carefully engineered resonator provides both mid-circuit erasure detection and end-of-line (EOL) logical measurement. Post-selection on non-erasure outcomes results in more than four-fold increase of the logical lifetime, from $193~μ$s to $869~μ$s. Finally, we characterize measurement-induced logical dephasing as a function of measurement power and frequency, and infer that each erasure check contributes a negligible error of $7.2\\times 10^{-5}$. These results establish integer-fluxonium as a promising, resource-efficient platform for erasure-based error mitigation, without requiring additional hardware.",
  "categories": [
    "quant-ph"
  ],
  "primary_category": "quant-ph",
  "comment": null,
  "published_date": "2026-01-16T08:39:04Z",
  "updated_date": "2026-01-16T08:39:04Z",
  "url": "https://arxiv.org/abs/2601.11086v1",
  "pdf_url": "https://arxiv.org/pdf/2601.11086v1.pdf",
  "source": "arxiv",
  "acquired_date": "2026-01-18T21:18:36.094982",
  "category": "physics",
  "subcategories": [
    "quant-ph"
  ]
}