{
  "id": "crossref_10.3109_9781420020229-33",
  "doi": "10.3109/9781420020229-33",
  "title": "Electrophrenic Respiration",
  "authors": [],
  "author_string": "",
  "journal": "Ventilatory Support for Chronic Respiratory Failure",
  "issn": null,
  "issn_type": "",
  "volume": "",
  "issue": "",
  "page": "371-380",
  "year": "2008",
  "publisher": "CRC Press",
  "language": "en",
  "abstract": "",
  "subjects": [],
  "keywords": [],
  "article_type": "book-chapter",
  "citation_count": 0,
  "url": "https://doi.org/10.3109/9781420020229-33",
  "source": "crossref",
  "acquired_date": "2026-02-03T13:36:34.173352",
  "category": "interdisciplinary",
  "subcategories": []
}