{
  "id": "crossref_10.1016_0006-3002(61)90623-0",
  "doi": "10.1016/0006-3002(61)90623-0",
  "title": "The biosynthesis of p-aminobenzoic acid: studies on the origin of the amino group",
  "authors": [
    "Srinivasan, P.R.",
    "Weiss, B."
  ],
  "author_string": "Srinivasan, P.R., Weiss, B.",
  "journal": "Biochimica et Biophysica Acta",
  "issn": "0006-3002",
  "issn_type": "print",
  "volume": "51",
  "issue": "3",
  "page": "597-599",
  "year": "1961",
  "publisher": "Elsevier BV",
  "language": "en",
  "abstract": "",
  "subjects": [],
  "keywords": [],
  "article_type": "journal-article",
  "citation_count": 17,
  "url": "https://doi.org/10.1016/0006-3002(61)90623-0",
  "source": "crossref",
  "acquired_date": "2026-02-03T14:04:02.003466",
  "category": "interdisciplinary",
  "subcategories": []
}