{
  "id": "crossref_10.1111_j.1365-2044.1950.tb13692.x",
  "doi": "10.1111/j.1365-2044.1950.tb13692.x",
  "title": "STUDIES IN DIFFUSION RESPIRATION",
  "authors": [],
  "author_string": "",
  "journal": "Anaesthesia",
  "issn": "0003-2409",
  "issn_type": "print",
  "volume": "5",
  "issue": "1",
  "page": "50-51",
  "year": "1950",
  "publisher": "Wiley",
  "language": "en",
  "abstract": "",
  "subjects": [],
  "keywords": [],
  "article_type": "journal-article",
  "citation_count": 1,
  "url": "https://doi.org/10.1111/j.1365-2044.1950.tb13692.x",
  "source": "crossref",
  "acquired_date": "2026-02-03T13:36:58.516035",
  "category": "interdisciplinary",
  "subcategories": []
}