{
  "id": "arxiv_2605.06604v1",
  "arxiv_id": "2605.06604v1",
  "title": "A Geometry-Aware Residual Correction of Hagan's SABR Implied Volatility Formula",
  "authors": [
    "Adil Reghai",
    "Lama Tarsissi",
    "Gérard Biau",
    "Alex Lipton"
  ],
  "author_string": "Adil Reghai, Lama Tarsissi, Gérard Biau, Alex Lipton",
  "journal": "arXiv:2605.06604v1",
  "journal_ref": null,
  "year": "2026",
  "doi": null,
  "abstract": "This paper proposes a hybrid methodology to improve the approximation of SABR (Stochastic Alpha Beta Rho) implied volatility by combining analytical structure with machine learning. The approach augments the neural-network input representation with geometric features derived from the stochastic differential equations of the SABR model. Unlike approaches that fully replace analytical formulas with black-box models, the proposed framework preserves the analytical backbone of the model. The hybridization operates along two complementary dimensions. First, geometry-aware variables reflecting intrinsic properties of the SABR dynamics are used as structured inputs to the network. Second, the neural network is trained to learn the residual error relative to Hagan's closed-form approximation rather than implied volatility directly. The resulting model acts as a structured residual correction to the analytical formula, retaining interpretability while capturing higher-order effects that are not included in the asymptotic expansion. Numerical experiments conducted over realistic parameter domains, as well as stressed environments, show that the method improves accuracy and robustness compared with both analytical approximations and standard neural-network approaches. Because the correction remains lightweight and structurally consistent with the underlying model, the framework is well suited for real-time pricing and calibration in practical trading environments.",
  "categories": [
    "q-fin.CP",
    "stat.ML"
  ],
  "primary_category": "stat.ML",
  "comment": "33 pages, 17 figures",
  "published_date": "2026-05-07T17:22:39Z",
  "updated_date": "2026-05-07T17:22:39Z",
  "url": "https://arxiv.org/abs/2605.06604v1",
  "pdf_url": "https://arxiv.org/pdf/2605.06604v1.pdf",
  "source": "arxiv",
  "acquired_date": "2026-05-09T22:15:44.049968",
  "category": "mathematics",
  "subcategories": [
    "q-fin.CP",
    "stat.ML"
  ]
}