{
  "id": "pubmed_32121161",
  "pmid": "32121161",
  "title": "Molecular Epidemiology of HIV-1 Infected Migrants Followed up in Portugal: Trends between 2001-2017.",
  "authors": [
    "Pimentel, Victor",
    "Pingarilho, Marta",
    "Alves, Daniela",
    "Diogo, Isabel",
    "Fernandes, Sandra",
    "Miranda, Mafalda",
    "Pineda-Pena, Andrea-Clemencia",
    "Libin, Pieter",
    "Martins, M Rosário O",
    "Vandamme, Anne-Mieke",
    "Camacho, Ricardo",
    "Gomes, Perpétua",
    "Abecasis, Ana"
  ],
  "author_string": "Pimentel, Victor, Pingarilho, Marta, Alves, Daniela, Diogo, Isabel, Fernandes, Sandra et al.",
  "journal": "Viruses",
  "journal_full": "Viruses",
  "year": "",
  "doi": "10.3390/v12030268",
  "abstract": "Migration is associated with HIV-1 vulnerability. To identify long-term trends in HIV-1 molecular epidemiology and antiretroviral drug resistance (ARV) among migrants followed up in Portugal Methods: 5177 patients were included between 2001 and 2017. Rega, Scuel, Comet, and jPHMM algorithms were used for subtyping. Transmitted drug resistance (TDR) and Acquired drug resistance (ADR) were defined as the presence of surveillance drug resistance mutations (SDRMs) and as mutations of the IAS-USA 2015 algorithm, respectively. Statistical analyses were performed. HIV-1 subtypes infecting migrants were consistent with the ones prevailing in their countries of origin. Over time, overall TDR significantly increased and specifically for Non-nucleoside reverse transcriptase inhibitor (NNRTIs) and Nucleoside reverse transcriptase inhibitor (NRTIs). TDR was higher in patients from Mozambique. Country of origin Mozambique and subtype B were independently associated with TDR. Overall, ADR significantly decreased over time and specifically for NRTIs and Protease Inhibitors (PIs). Age, subtype B, and viral load were independently associated with ADR. HIV-1 molecular epidemiology in migrants suggests high levels of connectivity with their country of origin. The increasing levels of TDR in migrants could indicate an increase also in their countries of origin, where more efficient surveillance should occur.",
  "keywords": [
    "HIV drug resistance mutations",
    "migrants",
    "molecular epidemiology"
  ],
  "citation_count": null,
  "url": "https://pubmed.ncbi.nlm.nih.gov/32121161",
  "source": "pubmed",
  "acquired_date": "2026-01-10T16:57:46.374654",
  "category": "biology",
  "subcategories": []
}