{
  "id": "pubmed_37985017",
  "pmid": "37985017",
  "title": "A well child with prolonged oral thrush: an unexpected diagnostic journey.",
  "authors": [
    "Gounari, Eleni",
    "Elfeky, Reem",
    "Ghataore, Lea",
    "Muhi-Iddin, Nadia",
    "Buchanan, Charles R",
    "Arya, Ved Bhushan"
  ],
  "author_string": "Gounari, Eleni, Elfeky, Reem, Ghataore, Lea, Muhi-Iddin, Nadia, Buchanan, Charles R et al.",
  "journal": "Arch Dis Child Educ Pract Ed",
  "journal_full": "Archives of disease in childhood. Education and practice edition",
  "year": "",
  "doi": "10.1136/archdischild-2023-325497",
  "abstract": "Oral thrush is a familiar presentation in both general practice and paediatrics, and is usually responsive to treatment in the community. Here, we present the diagnostic journey of a previously well boy aged 3 years who presented with treatment-resistant thrush and describe how 'unexpected' results led to eventual diagnosis and management. This intriguing case was managed jointly by district hospital general paediatric team and tertiary hospital specialist teams.",
  "keywords": [
    "allergy and Immunology",
    "endocrinology",
    "paediatrics"
  ],
  "citation_count": null,
  "url": "https://pubmed.ncbi.nlm.nih.gov/37985017",
  "source": "pubmed",
  "acquired_date": "2026-01-10T17:00:30.152790",
  "category": "biology",
  "subcategories": []
}