{
  "id": "pubmed_39260174",
  "pmid": "39260174",
  "title": "Impact of cultivar types and thermal processing methods on sweet potato metabolome, a comparative analysis via a multiplex approach of NIR and GC-MS based metabolomics coupled with chemometrics.",
  "authors": [
    "Ibrahim, Rana M",
    "Sedeek, Mohamed S",
    "Wareth, Amr Abdel",
    "R Khalifa, Mohamed",
    "Gendy, Abd El Monem",
    "Farag, Mohamed A"
  ],
  "author_string": "Ibrahim, Rana M, Sedeek, Mohamed S, Wareth, Amr Abdel, R Khalifa, Mohamed, Gendy, Abd El Monem et al.",
  "journal": "Food Chem",
  "journal_full": "Food chemistry",
  "year": "",
  "doi": "10.1016/j.foodchem.2024.141125",
  "abstract": "This study comprehensively analyzes the primary metabolites of sweet potato peels and pulps from four cultivars and assesses the impact of four different processing methods on pulp metabolome using a multiplex metabolomics approach of GC-MS and NIR. A total of 69 metabolites were identified. Beauregard cv. showed the highest sugar content (387.85 mg/g), whereas Sahrawy cv. was higher in alcohols (24.63 mg/g) and organic acids (2.98 mg/g). The chemometric analysis identified key markers that distinguished each cv. represented by its pulp, peel, and processed pulp. KEGG enrichment analysis pinpointed key metabolic pathways leading to the metabolic discrepancy of the specimens. Sugars were the most altered class by processing as manifested by a 5 to 11-fold increase, notably in the air-fried pulp. Air-frying also increased alcohol and organic acid contents. NIR analysis revealed that air-frying was the preferred method of processing, preserving the majority of pulp's metabolites, including β-carotene and phenolics.",
  "keywords": [
    "Chemometrics",
    "GC–MS",
    "Metabolomics",
    "NIR",
    "Processing methods",
    "Sweet potato"
  ],
  "citation_count": null,
  "url": "https://pubmed.ncbi.nlm.nih.gov/39260174",
  "source": "pubmed",
  "acquired_date": "2026-01-10T16:59:00.688327",
  "category": "biology",
  "subcategories": []
}