{
  "id": "pubmed_34735784",
  "pmid": "34735784",
  "title": "Panayiota Poirazi.",
  "authors": [],
  "author_string": "",
  "journal": "Neuron",
  "journal_full": "Neuron",
  "year": "",
  "doi": "10.1016/j.neuron.2021.09.049",
  "abstract": "In this Neuron Q&A, Panayiota Poirazi reflects on this past year's lessons and shares her not-so-direct trajectory in pursuit of her passion for neuroscience. Reminding us that science is a team game, she shares actionable steps to improve representation in science.",
  "keywords": [],
  "citation_count": null,
  "url": "https://pubmed.ncbi.nlm.nih.gov/34735784",
  "source": "pubmed",
  "acquired_date": "2026-01-10T17:01:26.802426",
  "category": "biology",
  "subcategories": []
}