{
  "id": "pubmed_39505436",
  "pmid": "39505436",
  "title": "[Not Available].",
  "authors": [
    "Bani, Mohamed Amine",
    "Moog, Sophie",
    "Suciu, Voichita",
    "Lamartina, Livia",
    "Ghuzlan, Abir Al"
  ],
  "author_string": "Bani, Mohamed Amine, Moog, Sophie, Suciu, Voichita, Lamartina, Livia, Ghuzlan, Abir Al",
  "journal": "Bull Cancer",
  "journal_full": "Bulletin du cancer",
  "year": "",
  "doi": "10.1016/S0007-4551(24)00404-1",
  "abstract": "WHO CLASSIFICATION 2022, BETHESDA SYSTEM 2023, MOLECULAR BIOLOGY AND MOLECULAR TESTING: Thyroid pathology has experienced significant advances with the publication of the 5th edition of the World Health Organization classification of endocrine tumors in 2022 and the third edition of the Bethesda system for thyroid cytopathology in 2023. At the same time, the availability of next-generation sequencing data coupled with numerous translational research projects have considerably increased our knowledge of the genomics and mechanics of thyroid cancers, enabling us to refine prognosis and propose new targeted therapies. In this review, we will take up the main new features of the WHO 2022 and Bethesda 2023 classifications, as well as molecular biology findings, with an emphasis on the practical implications for clinicians.",
  "keywords": [
    "Bethesda system",
    "Classification OMS",
    "Cytopathologie thyroïdienne",
    "Pathologie thyroïdienne",
    "Système Bethesda",
    "Thyroid cytopathology",
    "Thyroid pathology",
    "Thyroid tumors",
    "Tumeurs thyroïdiennes",
    "WHO classification"
  ],
  "citation_count": null,
  "url": "https://pubmed.ncbi.nlm.nih.gov/39505436",
  "source": "pubmed",
  "acquired_date": "2026-01-10T16:58:13.150732",
  "category": "biology",
  "subcategories": []
}