{
  "id": "pubmed_40931006",
  "pmid": "40931006",
  "title": "Academic leadership careers are not limited to scientific research.",
  "authors": [
    "Borger, Jessica G",
    "Hickey, Danica",
    "Habel, Jennifer R",
    "Rudd-McMahon, Callan",
    "Parnell, Grant",
    "Turner, Stephen J",
    "Wijburg, Odilia",
    "Dvorscek, Alexandra R"
  ],
  "author_string": "Borger, Jessica G, Hickey, Danica, Habel, Jennifer R, Rudd-McMahon, Callan, Parnell, Grant et al.",
  "journal": "Immunol Cell Biol",
  "journal_full": "Immunology and cell biology",
  "year": "",
  "doi": "10.1111/imcb.70057",
  "abstract": "Early career researchers (ECRs) are often faced with uncertainty about their professional futures, a challenge exacerbated by the increasing pressures within the academic research landscape. As ECRs navigate their next steps in science, mentorship is crucial, particularly as they face points of decision-making and possible career diversions from the traditional postdoctoral-to-professor pathway. In response to these challenges, the second iteration of the Australian and New Zealand Society of Immunology (ASI) Mentor-Mentee Program aimed to provide mentorship and training to ECRs about academic career pathways in research and education to bridge the professional communities, values and advice of these two often independent career choices. As a component of the program, three eminent Australian immunologists in research-intensive, teaching and research (TnR) and education-focused careers shared their professional journeys and experiences which led to their chosen career pathways in national workshops. Here, we share their insights, lessons learned and professional development tips to establish an academic career. By outlining the three primary scientific academic career pathways available post-PhD, we aim to inform and inspire the next generation of immunologists as they consider the diversity of possible academic careers ahead.",
  "keywords": [
    "academia",
    "careers",
    "education",
    "immunology",
    "research",
    "teaching"
  ],
  "citation_count": null,
  "url": "https://pubmed.ncbi.nlm.nih.gov/40931006",
  "source": "pubmed",
  "acquired_date": "2026-01-10T17:00:04.189946",
  "category": "biology",
  "subcategories": []
}