{
  "id": "pubmed_36863536",
  "pmid": "36863536",
  "title": "Discordance between semi-quantitative nucleic acid detection of bacteria and quantitative bacteriology in sputum from patients with pneumonia.",
  "authors": [
    "Gadsby, Naomi J",
    "Dunn, James J",
    "Johnson, Coreen L",
    "McQuillan, Taylor",
    "McHugh, Martin P",
    "Templeton, Kate E",
    "Rodriguez-Barradas, Maria C",
    "Musher, Daniel M"
  ],
  "author_string": "Gadsby, Naomi J, Dunn, James J, Johnson, Coreen L, McQuillan, Taylor, McHugh, Martin P et al.",
  "journal": "J Infect",
  "journal_full": "The Journal of infection",
  "year": "",
  "doi": "10.1016/j.jinf.2023.02.036",
  "abstract": "",
  "keywords": [],
  "citation_count": null,
  "url": "https://pubmed.ncbi.nlm.nih.gov/36863536",
  "source": "pubmed",
  "acquired_date": "2026-01-10T17:02:48.400417",
  "category": "biology",
  "subcategories": []
}