{
  "id": "pubmed_32185834",
  "pmid": "32185834",
  "title": "Celebrating the career and legacy of Professor Pascale Cossart.",
  "authors": [
    "Buchrieser, Carmen"
  ],
  "author_string": "Buchrieser, Carmen",
  "journal": "Mol Microbiol",
  "journal_full": "Molecular microbiology",
  "year": "",
  "doi": "10.1111/mmi.14478",
  "abstract": "",
  "keywords": [],
  "citation_count": null,
  "url": "https://pubmed.ncbi.nlm.nih.gov/32185834",
  "source": "pubmed",
  "acquired_date": "2026-01-10T16:59:31.073150",
  "category": "biology",
  "subcategories": []
}