{
  "id": "pubmed_38738732",
  "pmid": "38738732",
  "title": "Erythritol allergy.",
  "authors": [
    "Bosi, Isabelle",
    "Ford, Lara S"
  ],
  "author_string": "Bosi, Isabelle, Ford, Lara S",
  "journal": "J Paediatr Child Health",
  "journal_full": "Journal of paediatrics and child health",
  "year": "",
  "doi": "10.1111/jpc.16565",
  "abstract": "",
  "keywords": [],
  "citation_count": null,
  "url": "https://pubmed.ncbi.nlm.nih.gov/38738732",
  "source": "pubmed",
  "acquired_date": "2026-01-10T17:00:47.753714",
  "category": "biology",
  "subcategories": []
}