{
  "id": "pubmed_32860237",
  "pmid": "32860237",
  "title": "Premature aging disorders: A clinical and genetic compendium.",
  "authors": [
    "Schnabel, Franziska",
    "Kornak, Uwe",
    "Wollnik, Bernd"
  ],
  "author_string": "Schnabel, Franziska, Kornak, Uwe, Wollnik, Bernd",
  "journal": "Clin Genet",
  "journal_full": "Clinical genetics",
  "year": "",
  "doi": "10.1111/cge.13837",
  "abstract": "Progeroid disorders make up a heterogeneous group of very rare hereditary diseases characterized by clinical signs that often mimic physiological aging in a premature manner. Apart from Hutchinson-Gilford progeria syndrome, one of the best-investigated progeroid disorders, a wide spectrum of other premature aging phenotypes exist, which differ significantly in their clinical presentation and molecular pathogenesis. Next-generation sequencing (NGS)-based approaches have made it feasible to determine the molecular diagnosis in the early stages of a disease. Nevertheless, a broad clinical knowledge on these disorders and their associated symptoms is still fundamental for a comprehensive patient management and for the interpretation of variants of unknown significance from NGS data sets. This review provides a detailed overview on characteristic clinical features and underlying molecular genetics of well-known as well as only recently identified premature aging disorders and also highlights novel findings towards future therapeutic options.",
  "keywords": [
    "characteristic clinical features",
    "hereditary",
    "premature aging",
    "progeroid disorders"
  ],
  "citation_count": null,
  "url": "https://pubmed.ncbi.nlm.nih.gov/32860237",
  "source": "pubmed",
  "acquired_date": "2026-01-10T16:57:41.552362",
  "category": "biology",
  "subcategories": []
}