{
  "id": "pubmed_37805225",
  "pmid": "37805225",
  "title": "Answering the Call for Trustworthy Clinical Guidelines.",
  "authors": [
    "Shaker, Marcus S",
    "Lieberman, Jay A",
    "Lang, David M"
  ],
  "author_string": "Shaker, Marcus S, Lieberman, Jay A, Lang, David M",
  "journal": "J Allergy Clin Immunol Pract",
  "journal_full": "The journal of allergy and clinical immunology. In practice",
  "year": "",
  "doi": "10.1016/j.jaip.2023.07.046",
  "abstract": "",
  "keywords": [],
  "citation_count": null,
  "url": "https://pubmed.ncbi.nlm.nih.gov/37805225",
  "source": "pubmed",
  "acquired_date": "2026-01-10T17:00:50.594487",
  "category": "biology",
  "subcategories": []
}