{
  "id": "pubmed_20167139",
  "pmid": "20167139",
  "title": "Forensic approach to medical causation when allergic disease is in the differential diagnosis.",
  "authors": [
    "Weiner, Howard M"
  ],
  "author_string": "Weiner, Howard M",
  "journal": "Allergy Asthma Proc",
  "journal_full": "Allergy and asthma proceedings",
  "year": "",
  "doi": "10.2500/aap.2010.31.3303",
  "abstract": "As physicians, we are advocates for our patients. As allergists, we probe patient exposures. Occasionally, our good intentions find us entwined with forensic matters. Unfortunately, we have little formal training in toxicological, epidemiological, or evidence-based medicine methodology when determining exposure-related medical causation. This article provides such an approach and suggests helpful hints of conduct.",
  "keywords": [],
  "citation_count": null,
  "url": "https://pubmed.ncbi.nlm.nih.gov/20167139",
  "source": "pubmed",
  "acquired_date": "2026-01-13T20:30:37.952098",
  "category": "biology",
  "subcategories": []
}