{
  "id": "pubmed_31279431",
  "pmid": "31279431",
  "title": "Breast Cancer Demographics, Types and Management Pathways: Can Western Algorithms be Optimally used in Eastern Countries?",
  "authors": [
    "Chakraborty, S",
    "Wadasadawala, T",
    "Ahmed, R",
    "Coles, C",
    "Chatterjee, S"
  ],
  "author_string": "Chakraborty, S, Wadasadawala, T, Ahmed, R, Coles, C, Chatterjee, S",
  "journal": "Clin Oncol (R Coll Radiol)",
  "journal_full": "Clinical oncology (Royal College of Radiologists (Great Britain))",
  "year": "",
  "doi": "10.1016/j.clon.2019.05.024",
  "abstract": "Over the past decade, breast cancer has overtaken cervical cancer to become the most common cancer among women in India, as in most Western nations. In addition to the high incidence, the morbidity and mortality associated with this malignancy are disproportionately higher in India. Although some efforts are being made to increase awareness about this disease, a large majority of Indian patients present with advanced disease. Here, important institutional data and treatment outcomes are reviewed and compared with data from the West. Additionally, we highlight recent efforts in setting up collaborative multicentre trials in breast cancer in India and suggest some ways forward to improve outcomes.",
  "keywords": [
    "Breast cancer",
    "India",
    "UK",
    "breast surgery",
    "hypofractionation",
    "immunohistochemistry"
  ],
  "citation_count": null,
  "url": "https://pubmed.ncbi.nlm.nih.gov/31279431",
  "source": "pubmed",
  "acquired_date": "2026-01-13T20:29:06.004857",
  "category": "biology",
  "subcategories": []
}