{
  "id": "pubmed_23567155",
  "pmid": "23567155",
  "title": "Contextual models and the non-Newtonian paradigm.",
  "authors": [
    "Kitto, Kirsty",
    "Kortschak, R Daniel"
  ],
  "author_string": "Kitto, Kirsty, Kortschak, R Daniel",
  "journal": "Prog Biophys Mol Biol",
  "journal_full": "Progress in biophysics and molecular biology",
  "year": "",
  "doi": "10.1016/j.pbiomolbio.2013.03.011",
  "abstract": "Biological systems exhibit a wide range of contextual effects, and this often makes it difficult to construct valid mathematical models of their behaviour. In particular, mathematical paradigms built upon the successes of Newtonian physics make assumptions about the nature of biological systems that are unlikely to hold true. After discussing two of the key assumptions underlying the Newtonian paradigm, we discuss two key aspects of the formalism that extended it, Quantum Theory (QT). We draw attention to the similarities between biological and quantum systems, motivating the development of a similar formalism that can be applied to the modelling of biological processes.",
  "keywords": [
    "Biological models",
    "Contextuality",
    "Non-separability"
  ],
  "citation_count": null,
  "url": "https://pubmed.ncbi.nlm.nih.gov/23567155",
  "source": "pubmed",
  "acquired_date": "2026-01-13T20:28:34.841087",
  "category": "biology",
  "subcategories": []
}