{
  "id": "pubmed_8977898",
  "pmid": "8977898",
  "title": "[Critical analysis of isolation, counting and identification methods of Listeria in food industry].",
  "authors": [
    "Bind, J L",
    "Avoyne, C",
    "Delaval, J"
  ],
  "author_string": "Bind, J L, Avoyne, C, Delaval, J",
  "journal": "Pathol Biol (Paris)",
  "journal_full": "Pathologie-biologie",
  "year": "",
  "doi": null,
  "abstract": "Stimulated by epidemic outbreaks in years 80's and 90's detection methods for Listeria, and L. monocytogenes particularly, have undergone many important progresses. New selective media for isolation and enrichment have been formulated with the aim to improve bacteriological methods and decrease time delays. For identification of Listeria at the species level, some biochemical miniaturised tests allow response within 24 h. Within the immuno-chemical methods as ELISA or ELFA, the revelation step has been shortened and automated. The elaboration of L. monocytogenes specific antibodies begins to upset immunological methods. As far as concern simplification of detection tests, a new generation of small immunological plate-shaped tests has been marketed. Whatever the immunological method considered, intrinsic sensibility is about 10(5) at 10(6) CFU/ml. Only one method allows more sensibility: the immuno-magnetic separation. With a sensibility of 1 CFU/ml, immunocapture allows shortening of enrichment time of 24 h or eliminates this step altogether if the aim is to count the Listeria directly in the sample. In the biological molecular methods, some hybridization tests with nuclear probes allow rapid and specific detection of L. monocytogenes. The polymerase chain reaction has been improved to simplify and shorten the DNA preparation and the revelation of amplified fragments. This method will be soon used in food samples analysis. The elaboration of new methods that could allow the specific detection of L. monocytogenes pathogenic strains of is one of future stake.",
  "keywords": [],
  "citation_count": null,
  "url": "https://pubmed.ncbi.nlm.nih.gov/8977898",
  "source": "pubmed",
  "acquired_date": "2026-01-13T20:30:41.636107",
  "category": "biology",
  "subcategories": []
}