{
  "id": "pubmed_31264432",
  "pmid": "31264432",
  "title": "Laboratory Work-Up of Chronic B-Cell Lymphoid Malignancies - A Value-Based Approach.",
  "authors": [
    "Shi, Min",
    "Dao, Linda",
    "Jevremovic, Dragan"
  ],
  "author_string": "Shi, Min, Dao, Linda, Jevremovic, Dragan",
  "journal": "Acta Med Acad",
  "journal_full": "Acta medica academica",
  "year": "",
  "doi": "10.5644/ama2006-124.241",
  "abstract": "The aim of study was to summarize recent developments in laboratory work-up of lymphomas and discuss their clinical relevance. Diagnosis of lymphoma requires tissue biopsy with adequate work-up by pathologists. Recent developments in laboratory testing have raised the bar for establishing the diagnosis: more and more testing seems to be required, while the lines between research and clinical practice are being blurred. Academic medical practice is designed to push boundaries and test new hypotheses, which eventually result in improved patient care. Ability to (relatively) cheaply screen for multiple genomic abnormalities using new technologies is luring. Often, however, no change in patient management is pursued based on these results. It is therefore useful to review which testing is truly necessary from the patient's point of view. CONCLUSIONS: The laboratory work-up of lymphomas in a regular clinical practice requires relatively few tests. Many new tests have prognostic value, but do not necessarily contribute to the patient management.",
  "keywords": [
    "Lymphoma",
    "Pathology",
    "Prognosis"
  ],
  "citation_count": null,
  "url": "https://pubmed.ncbi.nlm.nih.gov/31264432",
  "source": "pubmed",
  "acquired_date": "2026-01-13T20:30:16.811389",
  "category": "biology",
  "subcategories": []
}