{
  "id": "crossref_10.1016_s0375-9601(97)00974-2",
  "doi": "10.1016/s0375-9601(97)00974-2",
  "title": "Quantum computation in quantum-Hall systems",
  "authors": [
    "Privman, V.",
    "Vagner, I.D.",
    "Kventsel, G."
  ],
  "author_string": "Privman, V., Vagner, I.D., Kventsel, G.",
  "journal": "Physics Letters A",
  "issn": "0375-9601",
  "issn_type": "print",
  "volume": "239",
  "issue": "3",
  "page": "141-146",
  "year": "1998",
  "publisher": "Elsevier BV",
  "language": "en",
  "abstract": "",
  "subjects": [],
  "keywords": [],
  "article_type": "journal-article",
  "citation_count": 156,
  "url": "https://doi.org/10.1016/s0375-9601(97)00974-2",
  "source": "crossref",
  "acquired_date": "2026-01-19T10:54:22.558575",
  "category": "physics",
  "subcategories": []
}