{
  "id": "arxiv_2605.02849v1",
  "arxiv_id": "2605.02849v1",
  "title": "Active Sampling for Ultra-Low-Bit-Rate Video Compression via Conditional Controlled Diffusion",
  "authors": [
    "Amirhosein Javadi",
    "Shirin Saeedi Bidokhti",
    "Tara Javidi"
  ],
  "author_string": "Amirhosein Javadi, Shirin Saeedi Bidokhti, Tara Javidi",
  "journal": "arXiv:2605.02849v1",
  "journal_ref": null,
  "year": "2026",
  "doi": null,
  "abstract": "Diffusion models provide a powerful generative prior for perceptual reconstruction at ultra-low bitrates, but effective video compression requires controlling the generative process using highly compact conditioning signals. In this work, we present ActDiff-VC, a diffusion-based video compression framework for the ultra-low-bitrate regime. Our method partitions videos into variable-length segments, transmits keyframes only when needed, and summarizes temporal dynamics using a compact set of tracked point trajectories. Conditioned on these sparse signals, a conditional diffusion decoder synthesizes the remaining frames, enabling perceptually realistic reconstruction under severe rate constraints. To support this design, we introduce two mechanisms: content-adaptive keyframe selection and budget-aware sparse trajectory selection, which together enable compact yet effective conditioning for generative reconstruction. Experiments on the UVG and MCL-JCV benchmarks show that ActDiff-VC achieves up to 64.6\\% bitrate reduction at matched NIQE, improves KID by up to 64.6\\% and FID by up to 37.7\\% at comparable bitrates against strong learned codecs, and delivers favorable perceptual rate--distortion trade-offs relative to learned and diffusion-based baselines in the ultra-low-bitrate regime.",
  "categories": [
    "cs.CV"
  ],
  "primary_category": "cs.CV",
  "comment": "21 pages, 11 figures, 3 tables",
  "published_date": "2026-05-04T17:25:14Z",
  "updated_date": "2026-05-04T17:25:14Z",
  "url": "https://arxiv.org/abs/2605.02849v1",
  "pdf_url": "https://arxiv.org/pdf/2605.02849v1.pdf",
  "source": "arxiv",
  "acquired_date": "2026-05-05T10:15:47.084994",
  "category": "computer_science",
  "subcategories": [
    "cs.CV"
  ]
}