{
  "id": "arxiv_2604.25701v1",
  "arxiv_id": "2604.25701v1",
  "title": "Bayesian Rate Inference for Sequence Motif Dynamics in Systems of Reactive Nucleic Acids",
  "authors": [
    "Johannes Harth-Kitzerow",
    "Ulrich Gerland",
    "Torsten A. Enßlin"
  ],
  "author_string": "Johannes Harth-Kitzerow, Ulrich Gerland, Torsten A. Enßlin",
  "journal": "arXiv:2604.25701v1",
  "journal_ref": null,
  "year": "2026",
  "doi": null,
  "abstract": "The RNA world hypothesis suggests a pathway of how life emerged on early earth. It assumes that life started with RNA based systems, capable of storing, transmitting and replicating information, envisioning that monomers and short RNA oligomers interact to form longer strands, eventually becoming catalytically active ribozymes. Key reactions in RNA pools are hybridization, dehybridization, templated ligation, and cleavage. Those reactions depend on many environmental parameters and the wide range of possible configurations among interacting strands. In order to scan such high dimensional parameter spaces, efficient descriptions are needed. Motif rate equations project complex strand reactor dynamics onto sequence motif space. Here we present a Bayesian inference framework to infer their parameters from ligation count data produced by strand reactor simulations. This provides a framework to match the simpler motif rate equations to more complex simulations. Additionally, it is a step towards inferring reaction rate constants directly from experimental data, including rigorous uncertainty estimation. This could be an essential procedure to connect theory and experiment, and deepen our understanding of the essential features necessary for life to emerge.",
  "categories": [
    "physics.bio-ph",
    "physics.data-an",
    "q-bio.BM",
    "q-bio.MN",
    "q-bio.PE"
  ],
  "primary_category": "q-bio.PE",
  "comment": "18 pages, 8 figures, pre-submission",
  "published_date": "2026-04-28T14:28:37Z",
  "updated_date": "2026-04-28T14:28:37Z",
  "url": "https://arxiv.org/abs/2604.25701v1",
  "pdf_url": "https://arxiv.org/pdf/2604.25701v1.pdf",
  "source": "arxiv",
  "acquired_date": "2026-05-06T10:15:36.874454",
  "category": "biology",
  "subcategories": [
    "physics.bio-ph",
    "physics.data-an",
    "q-bio.BM"
  ]
}